<annotation>
	<folder>processed_data</folder>
	<filename>16-nograde-top.png</filename>
	<path>C:/Users/Neo/Desktop/cs543/pcb-auto-grader/data/processed_data/16-nograde-top.png</path>
	<source>
		<database>Unknown</database>
	</source>
	<size>
		<width>540</width>
		<height>426</height>
		<depth>3</depth>
	</size>
	<segmented>0</segmented>
	<object>
		<name>power_supply</name>
		<pose>Unspecified</pose>
		<truncated>0</truncated>
		<difficult>0</difficult>
		<bndbox>
			<xmin>27</xmin>
			<ymin>71</ymin>
			<xmax>178</xmax>
			<ymax>188</ymax>
		</bndbox>
	</object>
	<object>
		<name>capacitance</name>
		<pose>Unspecified</pose>
		<truncated>0</truncated>
		<difficult>0</difficult>
		<bndbox>
			<xmin>41</xmin>
			<ymin>240</ymin>
			<xmax>95</xmax>
			<ymax>269</ymax>
		</bndbox>
	</object>
	<object>
		<name>regulation</name>
		<pose>Unspecified</pose>
		<truncated>0</truncated>
		<difficult>0</difficult>
		<bndbox>
			<xmin>299</xmin>
			<ymin>299</ymin>
			<xmax>346</xmax>
			<ymax>366</ymax>
		</bndbox>
	</object>
	<object>
		<name>resistance</name>
		<pose>Unspecified</pose>
		<truncated>0</truncated>
		<difficult>0</difficult>
		<bndbox>
			<xmin>432</xmin>
			<ymin>249</ymin>
			<xmax>458</xmax>
			<ymax>355</ymax>
		</bndbox>
	</object>
	<object>
		<name>capacitance</name>
		<pose>Unspecified</pose>
		<truncated>0</truncated>
		<difficult>0</difficult>
		<bndbox>
			<xmin>312</xmin>
			<ymin>124</ymin>
			<xmax>365</xmax>
			<ymax>155</ymax>
		</bndbox>
	</object>
	<object>
		<name>LED</name>
		<pose>Unspecified</pose>
		<truncated>0</truncated>
		<difficult>0</difficult>
		<bndbox>
			<xmin>434</xmin>
			<ymin>131</ymin>
			<xmax>452</xmax>
			<ymax>180</ymax>
		</bndbox>
	</object>
</annotation>
